my_connector/__init__.py
my_connector/get_connection.py
mysql_connector_package-0.1.2.dist-info/METADATA
mysql_connector_package-0.1.2.dist-info/WHEEL
mysql_connector_package-0.1.2.dist-info/top_level.txt
mysql_connector_package-0.1.2.dist-info/RECORD
