Metadata-Version: 2.1
Name: mysql-connector-package
Version: 0.1.2
Summary: A simple MySQL connector using pymysql
Home-page: https://github.com/Harishdaga/mysql-connector-package
Author: Harish Daga
Author-email: theharishdaga@gmail.com
Classifier: Programming Language :: Python :: 3
Requires-Python: >=3
Requires-Dist: pymysql
